trademan/ETFS.png
trademan/__init__.py
trademan/data.py
trademan/etfs.csv
trademan/portfolio.py
trademan/snp500_members.csv
trademan/stock_info.csv
trademan-0.1.0.dist-info/licenses/AUTHORS.rst
trademan-0.1.0.dist-info/licenses/LICENSE
trademan-0.1.0.dist-info/METADATA
trademan-0.1.0.dist-info/WHEEL
trademan-0.1.0.dist-info/entry_points.txt
trademan-0.1.0.dist-info/top_level.txt
trademan-0.1.0.dist-info/RECORD
