Metadata-Version: 2.4
Name: trademan
Version: 0.1.0
Summary: Trade and analyze stocks with portfolio optimization
Author-email: Kevin Russell <kevin@ottermatics.com>
License: MIT
Project-URL: Homepage, https://github.com/ottermatics/trademan
Project-URL: Repository, https://github.com/ottermatics/trademan
Project-URL: Issues, https://github.com/ottermatics/trademan/issues
Keywords: trading,portfolio,optimization,stocks,finance
Classifier: Development Status :: 3 - Alpha
Classifier: Intended Audience :: Developers
Classifier: Intended Audience :: Financial and Insurance Industry
Classifier: Natural Language :: English
Classifier: Programming Language :: Python :: 3
Classifier: Programming Language :: Python :: 3.8
Classifier: Programming Language :: Python :: 3.9
Classifier: Programming Language :: Python :: 3.10
Classifier: Programming Language :: Python :: 3.11
Classifier: Programming Language :: Python :: 3.12
Classifier: Topic :: Office/Business :: Financial :: Investment
Classifier: Topic :: Scientific/Engineering :: Mathematics
Requires-Python: >=3.8
License-File: LICENSE
License-File: AUTHORS.rst
Requires-Dist: PyPortfolioOpt
Requires-Dist: randomname
Requires-Dist: numpy
Requires-Dist: scipy
Requires-Dist: cvxpy
Requires-Dist: yfinance
Requires-Dist: matplotlib
Requires-Dist: diskcache
Requires-Dist: scikit-learn
Requires-Dist: pandas
Requires-Dist: pytz
Provides-Extra: dev
Requires-Dist: pytest>=6.0; extra == "dev"
Requires-Dist: pytest-cov; extra == "dev"
Requires-Dist: black>=21.7b0; extra == "dev"
Requires-Dist: flake8>=3.7.8; extra == "dev"
Requires-Dist: bump2version>=1.0.1; extra == "dev"
Requires-Dist: wheel; extra == "dev"
Requires-Dist: twine; extra == "dev"
Requires-Dist: sphinx>=4.0.0; extra == "dev"
Requires-Dist: sphinx-rtd-theme; extra == "dev"
Requires-Dist: coverage>=4.5.4; extra == "dev"
Requires-Dist: tox>=3.14.0; extra == "dev"
Requires-Dist: watchdog>=0.9.0; extra == "dev"
Requires-Dist: tomli>=1.2.0; python_version < "3.11" and extra == "dev"
Dynamic: license-file
